{
"type": "FeatureCollection",
"name": "service_iowa",
"crs": { "type": "name", "properties": { "name": "urn:ogc:def:crs:OGC:1.3:CRS84" } },
"features": [
{ "type": "Feature", "properties": { "City": "Des Moines", "Type": "Service Stations", "Name": "Eagle", "Address": "2246 Hubble Boulevard", "GeoADD": "2246 Hubble Boulevard, Des Moines, Iowa", "Year": 1950, "COORD": "41.602353, -93.576177", "COORD_X": -93.576177, "COORD_Y": 41.602353, "Notes": "Used Hubble Avenue", "LAT": 41.602353, "LONG": -93.576177 }, "geometry": { "type": "Point", "coordinates": [ -93.57618, 41.60235 ] } },
{ "type": "Feature", "properties": { "City": "Des Moines", "Type": "Service Stations", "Name": "Mumford's", "Address": "4th Street and Euclid Avenue", "GeoADD": "4th Street and Euclid Avenue, Des Moines, Iowa", "Year": 1950, "COORD": "41.627686, -93.622286", "COORD_X": -93.622286, "COORD_Y": 41.627686, "Notes": null, "LAT": 41.627686, "LONG": -93.622286 }, "geometry": { "type": "Point", "coordinates": [ -93.62229, 41.62769 ] } }
]
}
